{"description":null,"media_type":"V1::MediaTypes::Hello","actions":[{"description":null,"name":"index","urls":[{"verb":"GET","path":"/api/hello","version":"1.0"}],"headers":{"options":{"reference":"V1::MediaTypes::Hello"},"type":{"name":"Struct","attributes":{"X_API_VERSION":{"values":["1.0"],"required":true,"type":{"name":"String"}}}}},"responses":{"ok":{"description":null,"status":200,"headers":{},"media_type":{"name":"V1::MediaTypes::Hello"}}}},{"description":null,"name":"show","urls":[{"verb":"GET","path":"/api/hello/:id","version":"1.0"}],"headers":{"options":{"reference":"V1::MediaTypes::Hello"},"type":{"name":"Struct","attributes":{"X_API_VERSION":{"values":["1.0"],"required":true,"type":{"name":"String"}}}}},"params":{"options":{"reference":"V1::MediaTypes::Hello"},"type":{"name":"Struct","attributes":{"id":{"required":true,"options":{"min":0},"type":{"name":"Integer"}}}},"example":{"id":8}},"responses":{"ok":{"description":null,"status":200,"headers":{},"media_type":{"name":"V1::MediaTypes::Hello"}}}}]}